{
  "sheets": [
    {
      "name": "Set Up Details",
      "order": 1,
      "sheet_type": "input",
      "migration_role": "form_module",
      "purpose": "Capture global business setup and model controls.",
      "year_scope": "multi-year",
      "is_user_facing": true,
      "primary_inputs": ["business profile", "global settings", "tax profile"],
      "primary_outputs": ["setup context for downstream sheets"],
      "depends_on": [],
      "feeds_into": ["Sales Details", "Key Assumptions Year 1", "Sales Forecast Year 1"],
      "notes": ["Canonical source for global assumptions."]
    },
    {
      "name": "Personal Cash Flow Budget Y1",
      "order": 2,
      "sheet_type": "mixed",
      "migration_role": "form_module",
      "purpose": "Capture personal cash movements relevant to year 1 planning.",
      "year_scope": "year1",
      "is_user_facing": true,
      "primary_inputs": ["personal income/expense assumptions", "owner movement assumptions"],
      "primary_outputs": ["owner cash movement adjustments"],
      "depends_on": ["Set Up Details"],
      "feeds_into": ["Cash Flow Year 1"],
      "notes": ["Needs confirmation on business vs personal boundary rules."]
    },
    {
      "name": "Assets and Depreciation",
      "order": 3,
      "sheet_type": "mixed",
      "migration_role": "form_module",
      "purpose": "Manage asset purchases and calculate depreciation effects.",
      "year_scope": "multi-year",
      "is_user_facing": true,
      "primary_inputs": ["asset class", "purchase value", "useful life"],
      "primary_outputs": ["depreciation expense", "asset carrying values"],
      "depends_on": ["Set Up Details", "Key Assumptions Year 1"],
      "feeds_into": ["Profit & Loss Statements", "Balance Sheets"],
      "notes": ["Depreciation logic should become a dedicated engine module."]
    },
    {
      "name": "Business Loans",
      "order": 4,
      "sheet_type": "mixed",
      "migration_role": "form_module",
      "purpose": "Define loan structures and repayment behavior.",
      "year_scope": "multi-year",
      "is_user_facing": true,
      "primary_inputs": ["principal", "interest rate", "term", "repayment frequency"],
      "primary_outputs": ["interest expense", "principal repayment", "liability balance"],
      "depends_on": ["Set Up Details"],
      "feeds_into": ["Cash Flow Year 1", "Cash Flow Year 2", "Cash Flow Year 3", "Profit & Loss Statements", "Balance Sheets"],
      "notes": ["Use amortization schedule module in web app."]
    },
    {
      "name": "Marketing Action Plan Year 1",
      "order": 5,
      "sheet_type": "input",
      "migration_role": "form_module",
      "purpose": "Capture year 1 marketing spend assumptions.",
      "year_scope": "year1",
      "is_user_facing": true,
      "primary_inputs": ["campaign spend", "timing", "category allocation"],
      "primary_outputs": ["monthly marketing expense values"],
      "depends_on": ["Set Up Details"],
      "feeds_into": ["Cash Flow Year 1", "Profit & Loss Statements"],
      "notes": ["Pattern repeated in Y2 and Y3."]
    },
    {
      "name": "Marketing Action Plan Year 2",
      "order": 6,
      "sheet_type": "input",
      "migration_role": "form_module",
      "purpose": "Capture year 2 marketing spend assumptions.",
      "year_scope": "year2",
      "is_user_facing": true,
      "primary_inputs": ["campaign spend", "timing", "category allocation"],
      "primary_outputs": ["monthly marketing expense values"],
      "depends_on": ["Set Up Details", "Key Assumptions Year 2"],
      "feeds_into": ["Cash Flow Year 2", "Profit & Loss Statements"],
      "notes": ["Should be config-driven with same schema as year 1."]
    },
    {
      "name": "Marketing Action Plan Year 3",
      "order": 7,
      "sheet_type": "input",
      "migration_role": "form_module",
      "purpose": "Capture year 3 marketing spend assumptions.",
      "year_scope": "year3",
      "is_user_facing": true,
      "primary_inputs": ["campaign spend", "timing", "category allocation"],
      "primary_outputs": ["monthly marketing expense values"],
      "depends_on": ["Set Up Details", "Key Assumptions Year 3"],
      "feeds_into": ["Cash Flow Year 3", "Profit & Loss Statements"],
      "notes": ["Should be config-driven with same schema as year 1."]
    },
    {
      "name": "Sales Details",
      "order": 8,
      "sheet_type": "input",
      "migration_role": "form_module",
      "purpose": "Define products/services and baseline sales assumptions.",
      "year_scope": "multi-year",
      "is_user_facing": true,
      "primary_inputs": ["product/service list", "price", "quantity", "frequency"],
      "primary_outputs": ["sales drivers for forecast sheets"],
      "depends_on": ["Set Up Details"],
      "feeds_into": ["Sales Forecast Year 1", "Sales Forecast Year 2", "Sales Forecast Year 3"],
      "notes": ["Core revenue driver domain."]
    },
    {
      "name": "Sales Forecast Year 1",
      "order": 9,
      "sheet_type": "mixed",
      "migration_role": "form_module",
      "purpose": "Generate month-by-month revenue and related metrics for year 1.",
      "year_scope": "year1",
      "is_user_facing": true,
      "primary_inputs": ["sales volume assumptions", "growth rates", "seasonality controls"],
      "primary_outputs": ["monthly sales totals", "annual sales totals"],
      "depends_on": ["Sales Details", "Key Assumptions Year 1"],
      "feeds_into": ["Debtors Analysis", "Cash Flow Year 1", "Profit & Loss Statements"],
      "notes": ["Reference implementation for year pattern."]
    },
    {
      "name": "Sales Forecast Year 2",
      "order": 10,
      "sheet_type": "mixed",
      "migration_role": "form_module",
      "purpose": "Generate month-by-month revenue and related metrics for year 2.",
      "year_scope": "year2",
      "is_user_facing": true,
      "primary_inputs": ["sales volume assumptions", "growth rates", "seasonality controls"],
      "primary_outputs": ["monthly sales totals", "annual sales totals"],
      "depends_on": ["Sales Details", "Key Assumptions Year 2"],
      "feeds_into": ["Debtors Analysis", "Cash Flow Year 2", "Profit & Loss Statements"],
      "notes": ["Should be generated from reusable year config."]
    },
    {
      "name": "Sales Forecast Year 3",
      "order": 11,
      "sheet_type": "mixed",
      "migration_role": "form_module",
      "purpose": "Generate month-by-month revenue and related metrics for year 3.",
      "year_scope": "year3",
      "is_user_facing": true,
      "primary_inputs": ["sales volume assumptions", "growth rates", "seasonality controls"],
      "primary_outputs": ["monthly sales totals", "annual sales totals"],
      "depends_on": ["Sales Details", "Key Assumptions Year 3"],
      "feeds_into": ["Debtors Analysis", "Cash Flow Year 3", "Profit & Loss Statements"],
      "notes": ["Should be generated from reusable year config."]
    },
    {
      "name": "Cash Flow Year 1",
      "order": 12,
      "sheet_type": "output",
      "migration_role": "report_module",
      "purpose": "Display year 1 cash inflows, outflows, and balances.",
      "year_scope": "year1",
      "is_user_facing": true,
      "primary_inputs": [],
      "primary_outputs": ["monthly net cash flow", "closing cash balances"],
      "depends_on": ["Sales Forecast Year 1", "Debtors Analysis", "Marketing Action Plan Year 1", "Business Loans", "Personal Cash Flow Budget Y1"],
      "feeds_into": ["Quarterly Results"],
      "notes": ["Core financial health output."]
    },
    {
      "name": "Cash Flow Year 2",
      "order": 13,
      "sheet_type": "output",
      "migration_role": "report_module",
      "purpose": "Display year 2 cash inflows, outflows, and balances.",
      "year_scope": "year2",
      "is_user_facing": true,
      "primary_inputs": [],
      "primary_outputs": ["monthly net cash flow", "closing cash balances"],
      "depends_on": ["Sales Forecast Year 2", "Debtors Analysis", "Marketing Action Plan Year 2", "Business Loans"],
      "feeds_into": ["Quarterly Results"],
      "notes": ["Core financial health output."]
    },
    {
      "name": "Cash Flow Year 3",
      "order": 14,
      "sheet_type": "output",
      "migration_role": "report_module",
      "purpose": "Display year 3 cash inflows, outflows, and balances.",
      "year_scope": "year3",
      "is_user_facing": true,
      "primary_inputs": [],
      "primary_outputs": ["monthly net cash flow", "closing cash balances"],
      "depends_on": ["Sales Forecast Year 3", "Debtors Analysis", "Marketing Action Plan Year 3", "Business Loans"],
      "feeds_into": ["Quarterly Results"],
      "notes": ["Core financial health output."]
    },
    {
      "name": "Profit & Loss Statements",
      "order": 15,
      "sheet_type": "output",
      "migration_role": "report_module",
      "purpose": "Provide accrual-based profitability summary.",
      "year_scope": "multi-year",
      "is_user_facing": true,
      "primary_inputs": [],
      "primary_outputs": ["revenue", "COGS", "gross profit", "operating profit", "net profit"],
      "depends_on": ["Sales Forecast Year 1", "Sales Forecast Year 2", "Sales Forecast Year 3", "Marketing Action Plan Year 1", "Marketing Action Plan Year 2", "Marketing Action Plan Year 3", "Business Loans", "Assets and Depreciation"],
      "feeds_into": ["Quarterly Results"],
      "notes": ["Needs consistency checks against cash flow and balance sheet."]
    },
    {
      "name": "Balance Sheets",
      "order": 16,
      "sheet_type": "output",
      "migration_role": "report_module",
      "purpose": "Report assets, liabilities, and equity positions.",
      "year_scope": "multi-year",
      "is_user_facing": true,
      "primary_inputs": [],
      "primary_outputs": ["asset totals", "liability totals", "equity totals", "balance check"],
      "depends_on": ["Cash Flow Year 1", "Cash Flow Year 2", "Cash Flow Year 3", "Debtors Analysis", "Assets and Depreciation", "Business Loans"],
      "feeds_into": ["Quarterly Results"],
      "notes": ["Likely high-risk if upstream formulas are inconsistent."]
    },
    {
      "name": "Key Assumptions Year 1",
      "order": 17,
      "sheet_type": "input",
      "migration_role": "form_module",
      "purpose": "Provide year 1 financial assumptions and rates.",
      "year_scope": "year1",
      "is_user_facing": true,
      "primary_inputs": ["tax assumptions", "inflation/CPI", "timing defaults"],
      "primary_outputs": ["assumption factors for forecasts and reports"],
      "depends_on": ["Set Up Details"],
      "feeds_into": ["Sales Forecast Year 1", "Cash Flow Year 1", "Profit & Loss Statements", "Assets and Depreciation"],
      "notes": ["Assumption provenance should be explicit in app UI."]
    },
    {
      "name": "Key Assumptions Year 2",
      "order": 18,
      "sheet_type": "input",
      "migration_role": "form_module",
      "purpose": "Provide year 2 financial assumptions and rates.",
      "year_scope": "year2",
      "is_user_facing": true,
      "primary_inputs": ["tax assumptions", "inflation/CPI", "timing defaults"],
      "primary_outputs": ["assumption factors for forecasts and reports"],
      "depends_on": ["Set Up Details"],
      "feeds_into": ["Sales Forecast Year 2", "Cash Flow Year 2", "Profit & Loss Statements"],
      "notes": ["Assumption model should use reusable schema."]
    },
    {
      "name": "Key Assumptions Year 3",
      "order": 19,
      "sheet_type": "input",
      "migration_role": "form_module",
      "purpose": "Provide year 3 financial assumptions and rates.",
      "year_scope": "year3",
      "is_user_facing": true,
      "primary_inputs": ["tax assumptions", "inflation/CPI", "timing defaults"],
      "primary_outputs": ["assumption factors for forecasts and reports"],
      "depends_on": ["Set Up Details"],
      "feeds_into": ["Sales Forecast Year 3", "Cash Flow Year 3", "Profit & Loss Statements"],
      "notes": ["Assumption model should use reusable schema."]
    },
    {
      "name": "Breakeven Analysis - Service",
      "order": 20,
      "sheet_type": "output",
      "migration_role": "report_module",
      "purpose": "Show break-even analysis for service-led model.",
      "year_scope": "multi-year",
      "is_user_facing": true,
      "primary_inputs": [],
      "primary_outputs": ["service break-even point", "contribution margin summary"],
      "depends_on": ["Sales Forecast Year 1", "Sales Forecast Year 2", "Sales Forecast Year 3", "Profit & Loss Statements"],
      "feeds_into": [],
      "notes": ["Methodology (cash vs accrual) must be confirmed."]
    },
    {
      "name": "Breakeven Analysis - Product",
      "order": 21,
      "sheet_type": "output",
      "migration_role": "report_module",
      "purpose": "Show break-even analysis for product-led model.",
      "year_scope": "multi-year",
      "is_user_facing": true,
      "primary_inputs": [],
      "primary_outputs": ["product break-even point", "contribution margin summary"],
      "depends_on": ["Sales Forecast Year 1", "Sales Forecast Year 2", "Sales Forecast Year 3", "Profit & Loss Statements"],
      "feeds_into": [],
      "notes": ["Should share a break-even engine with service model."]
    },
    {
      "name": "Quarterly Results",
      "order": 22,
      "sheet_type": "output",
      "migration_role": "report_module",
      "purpose": "Roll up monthly outputs into quarter-level reporting.",
      "year_scope": "multi-year",
      "is_user_facing": true,
      "primary_inputs": [],
      "primary_outputs": ["quarterly sales", "quarterly profitability", "quarterly cash signals"],
      "depends_on": ["Cash Flow Year 1", "Cash Flow Year 2", "Cash Flow Year 3", "Profit & Loss Statements", "Balance Sheets"],
      "feeds_into": [],
      "notes": ["Mostly reporting; avoid bespoke duplicate logic."]
    },
    {
      "name": "Tables and Calculations",
      "order": 23,
      "sheet_type": "calculation",
      "migration_role": "internal_engine_only",
      "purpose": "Central helper calculations and lookup bridges.",
      "year_scope": "multi-year",
      "is_user_facing": false,
      "primary_inputs": ["intermediate references"],
      "primary_outputs": ["derived helper values"],
      "depends_on": ["multiple upstream sheets"],
      "feeds_into": ["multiple downstream sheets"],
      "notes": ["High-risk for broken references; convert to explicit code modules."]
    },
    {
      "name": "Table2",
      "order": 24,
      "sheet_type": "reference",
      "migration_role": "internal_engine_only",
      "purpose": "Support reference data and helper mappings.",
      "year_scope": "n/a",
      "is_user_facing": false,
      "primary_inputs": ["reference constants", "helper mappings"],
      "primary_outputs": ["lookup values"],
      "depends_on": [],
      "feeds_into": ["Tables and Calculations", "other formula sheets"],
      "notes": ["Do not expose in UI; represent as typed constants/config."]
    },
    {
      "name": "Debtors Analysis",
      "order": 25,
      "sheet_type": "calculation",
      "migration_role": "internal_engine_only",
      "purpose": "Transform forecast revenue into timed cash collections and receivable balances.",
      "year_scope": "multi-year",
      "is_user_facing": false,
      "primary_inputs": ["sales forecast outputs", "collection timing assumptions"],
      "primary_outputs": ["cash receipt timing", "closing receivables"],
      "depends_on": ["Sales Forecast Year 1", "Sales Forecast Year 2", "Sales Forecast Year 3", "Key Assumptions Year 1", "Key Assumptions Year 2", "Key Assumptions Year 3"],
      "feeds_into": ["Cash Flow Year 1", "Cash Flow Year 2", "Cash Flow Year 3", "Balance Sheets"],
      "notes": ["Core engine domain; non-user-facing by design."]
    }
  ]
}
